yaqd_core/__init__.py
yaqd_core/__version__.py
yaqd_core/_has_dependents.py
yaqd_core/_has_limits.py
yaqd_core/_has_mapping.py
yaqd_core/_has_measure_trigger.py
yaqd_core/_has_position.py
yaqd_core/_has_transformed_position.py
yaqd_core/_has_turret.py
yaqd_core/_is_daemon.py
yaqd_core/_is_discrete.py
yaqd_core/_is_homeable.py
yaqd_core/_is_sensor.py
yaqd_core/_mro.py
yaqd_core/_protocol.py
yaqd_core/_state.py
yaqd_core/_uses_i2c.py
yaqd_core/_uses_serial.py
yaqd_core/_uses_uart.py
yaqd_core/py.typed
yaqd_core/_legacy/__init__.py
yaqd_core/_legacy/_base.py
yaqd_core/_legacy/_continuous.py
yaqd_core/_legacy/_discrete.py
yaqd_core/_legacy/_sensor.py
yaqd_core/aserial/__init__.py
yaqd_core/aserial/_aserial.py
yaqd_core/avrorpc/__init__.py
yaqd_core/avrorpc/avro_numpy.py
yaqd_core/avrorpc/handshake.py
yaqd_core/avrorpc/protocol.py
yaqd_core/avrorpc/unpacker.py
yaqd_core/logging/__init__.py
yaqd_core/testing/__init__.py
yaqd_core/testing/_run_daemon.py
yaqd_core-2025.12.0.dist-info/METADATA
yaqd_core-2025.12.0.dist-info/WHEEL
yaqd_core-2025.12.0.dist-info/licenses/LICENSE
yaqd_core-2025.12.0.dist-info/RECORD
