Metadata-Version: 2.4
Name: yaqd-core
Version: 2025.12.0
Summary: Core python package for implementing yaq daemons, and associated utilities.
Project-URL: Home Page, https://yaq.fyi
Project-URL: Source, https://github.com/yaq-project/yaq-python
Project-URL: Issues, https://github.com/yaq-project/yaq-python/issues
Author: yaq developers
License-Expression: LGPL-3.0-only
License-File: LICENSE
Classifier: Development Status :: 5 - Production/Stable
Classifier: Intended Audience :: Science/Research
Classifier: License :: OSI Approved :: GNU Lesser General Public License v3 (LGPLv3)
Classifier: Natural Language :: English
Classifier: Programming Language :: Python :: 3
Classifier: Programming Language :: Python :: 3.9
Classifier: Programming Language :: Python :: 3.10
Classifier: Programming Language :: Python :: 3.11
Classifier: Programming Language :: Python :: 3.12
Classifier: Programming Language :: Python :: 3.13
Classifier: Programming Language :: Python :: 3.14
Classifier: Topic :: Scientific/Engineering
Requires-Python: >=3.7
Requires-Dist: fastavro>=1.4.0
Requires-Dist: platformdirs
Requires-Dist: tomli
Requires-Dist: tomli-w
Provides-Extra: dev
Requires-Dist: black; extra == 'dev'
Requires-Dist: pre-commit; extra == 'dev'
